{
  "packages": [
    "kubectl@latest",
    "minikube@latest",
    "k3d@latest",
    "docker@latest",
    "go-task@latest",
    "termshot@latest",
    "kubernetes-helm@latest",
    "argocd@latest",
    "kind@latest",
    "kustomize@latest",
    "k6@latest",
    "trivy@latest",
    "opa@latest"
  ],
  "shell": {
    "init_hook": [
      "echo '🚀 Apollo 11 Devbox Environment Loaded'",
      "echo 'Tools available: kubectl, minikube, docker, task'"
    ],
    "scripts": {
      "test": "echo \"Error: no test specified\" && exit 1"
    }
  }
}
